rrweb/__init__.py
rrweb/rqUtil/=3.5.11
rrweb/rqUtil/__init__.py
rrweb/rqUtil/config_setting.py
rrweb/rqUtil/rqCache.py
rrweb/rqUtil/rqCode.py
rrweb/rqUtil/rqCsv.py
rrweb/rqUtil/rqDate.py
rrweb/rqUtil/rqDate_trade.py
rrweb/rqUtil/rqLocalize.py
rrweb/rqUtil/rqMysql.py
rrweb/rqUtil/rqMysqlClass.py
rrweb/rqUtil/rqParameter.py
rrweb/rqUtil/rqPgsql.py
rrweb/rqUtil/rqSingleton.py
rrweb/rqUtil/rqTrade_time.py
rrweb/rqUtil/rqTusharepro.py
rrweb/rqUtil/send_email.py
rrweb/rqUtil/trade_date_sse_list.py
rrweb/start_streamlit.sh
rrweb/stock_RS_OH_MA_to_streamlit.py
rrweb-0.1.1.dist-info/WHEEL
rrweb-0.1.1.dist-info/METADATA
rrweb-0.1.1.dist-info/RECORD
