Metadata-Version: 2.1
Name: rrweb
Version: 0.1.1
Summary: to web by streamlit
Author: romepeng
Author-email: romepeng@outlook.com
Requires-Python: >=3.8,<4.0
Classifier: Programming Language :: Python :: 3
Classifier: Programming Language :: Python :: 3.8
Classifier: Programming Language :: Python :: 3.9
